{
    "nodes": [
        {
            "id": "node-data",
            "type": "link",
            "label": "Example Data",
            "position": {
                "x": 100,
                "y": 250
            },
            "data": {
                "manualUrl": "https://github.com/baconlover209/Nodeplot/blob/main/public/exampleData.csv"
            },
            "inputs": {
                "url": null
            },
            "outputs": {
                "output": null
            }
        },
        {
            "id": "node-values",
            "type": "isolateColumn",
            "label": "Values",
            "position": {
                "x": 600,
                "y": 250
            },
            "data": {
                "columnIndex": 15
            },
            "inputs": {
                "csvData": null
            },
            "outputs": {
                "data": null
            }
        },
        {
            "id": "node-trace",
            "type": "trace",
            "label": "Violin Trace",
            "position": {
                "x": 1100,
                "y": 250
            },
            "data": {
                "type": "violin",
                "name": "Violin Example"
            },
            "inputs": {
                "y": null
            },
            "outputs": {
                "trace": null
            }
        },
        {
            "id": "node-plotly",
            "type": "plotly",
            "label": "Plotly Chart",
            "position": {
                "x": 1600,
                "y": 250
            },
            "data": {},
            "inputs": {
                "data": null,
                "layout": null
            },
            "outputs": {}
        }
    ],
    "connections": [
        {
            "id": "c1",
            "sourceNodeId": "node-data",
            "sourcePort": "output",
            "targetNodeId": "node-values",
            "targetPort": "csvData"
        },
        {
            "id": "c2",
            "sourceNodeId": "node-values",
            "sourcePort": "data",
            "targetNodeId": "node-trace",
            "targetPort": "y"
        },
        {
            "id": "c3",
            "sourceNodeId": "node-trace",
            "sourcePort": "trace",
            "targetNodeId": "node-plotly",
            "targetPort": "data"
        }
    ],
    "zoom": 0.8,
    "pan": {
        "x": 50,
        "y": 50
    }
}
